ytsaurus_rpc_driver-1.0.1.dist-info/METADATA
ytsaurus_rpc_driver-1.0.1.dist-info/top_level.txt
ytsaurus_rpc_driver-1.0.1.dist-info/WHEEL
ytsaurus_rpc_driver-1.0.1.dist-info/RECORD
yt_driver_rpc_bindings/driver.py
yt_driver_rpc_bindings/__init__.py
yt_driver_rpc_bindings/driver_rpc_lib.so
