Metadata-Version: 2.1
Name: ytsaurus-rpc-driver
Version: 1.0.1
Summary: C++ RPC driver.
Author: YTsaurus
Author-email: dev@ytsaurus.tech
License: Apache 2.0
Keywords: yt ytsaurus python bindings driver
